clustutils4r/__init__.py
clustutils4r/eval_clustering.py
clustutils4r-1.0.0.dist-info/LICENSE
clustutils4r-1.0.0.dist-info/METADATA
clustutils4r-1.0.0.dist-info/WHEEL
clustutils4r-1.0.0.dist-info/top_level.txt
clustutils4r-1.0.0.dist-info/RECORD
