Metadata-Version: 2.1
Name: clustutils4r
Version: 1.0.0
Summary: Wrapper around some basic sklearn utilities for clustering.
Home-page: https://github.com/rutujagurav/clustutils4r
Author: Rutuja Gurav
Author-email: Rutuja Gurav <rutujagurav100@gmail.com>
Project-URL: Homepage, https://github.com/rutujagurav/clustutils4r
Project-URL: Bug Tracker, https://github.com/rutujagurav/clustutils4r/issues
Classifier: Programming Language :: Python :: 3
Classifier: License :: OSI Approved :: MIT License
Classifier: Operating System :: OS Independent
Requires-Python: >=3.8
License-File: LICENSE
